clicerin/__init__.py
clicerin/ai/SYSTEM_PROMPT
clicerin/ai/__init__.py
clicerin/ai/chat.py
clicerin/ai/constant.py
clicerin/ai/model.py
clicerin/assistant.py
clicerin/helper/__init__.py
clicerin/helper/audio.py
clicerin/helper/db.py
clicerin/helper/file.py
clicerin/main.py
clicerin/stdio/__init__.py
clicerin/stdio/stdout.py
clicerin/tui/__init__.py
clicerin/tui/consultant.py
clicerin/tui/consultant.tcss
clicerin/version.py
clicerin-0.1.0.dist-info/METADATA
clicerin-0.1.0.dist-info/WHEEL
clicerin-0.1.0.dist-info/entry_points.txt
clicerin-0.1.0.dist-info/RECORD
