Metadata-Version: 2.1
Name: clicerin
Version: 0.1.0
Summary: CLI for your quality of life
Author: Irwanto Cia
Author-email: irwantocia@gmail.com
Requires-Python: >=3.12,<4.0
Classifier: Programming Language :: Python :: 3
Classifier: Programming Language :: Python :: 3.12
Classifier: Programming Language :: Python :: 3.13
Requires-Dist: asyncio (>=3.4.3,<4.0.0)
Requires-Dist: numpy (>=2.2.0,<3.0.0)
Requires-Dist: openai (>=1.57.1,<2.0.0)
Requires-Dist: pyaudio (>=0.2.14,<0.3.0)
Requires-Dist: pydub (>=0.25.1,<0.26.0)
Requires-Dist: requests (>=2.32.3,<3.0.0)
Requires-Dist: soundfile (>=0.12.1,<0.13.0)
Requires-Dist: textual (>=1.0.0,<2.0.0)
Requires-Dist: typer (>=0.15.1,<0.16.0)
